sphinx_ext_mystmd/__about__.py
sphinx_ext_mystmd/__init__.py
sphinx_ext_mystmd/builder.py
sphinx_ext_mystmd/transform.py
sphinx_ext_mystmd/utils.py
sphinx_ext_mystmd-0.0.0.dist-info/METADATA
sphinx_ext_mystmd-0.0.0.dist-info/WHEEL
sphinx_ext_mystmd-0.0.0.dist-info/RECORD
