Metadata-Version: 2.3
Name: sphinx-ext-mystmd
Version: 0.0.0
Summary: A Sphinx extension to build MyST-MD AST from a Sphinx project
Project-URL: Documentation, https://github.com/executablebooks/sphinx-ext-mystmd#readme
Project-URL: Issues, https://github.com/executablebooks/sphinx-ext-mystmd/issues
Project-URL: Source, https://github.com/executablebooks/sphinx-ext-mystmd
Author-email: Angus Hollands <goosey15@gmail.com>
License-Expression: MIT
Classifier: Development Status :: 4 - Beta
Classifier: Programming Language :: Python
Classifier: Programming Language :: Python :: 3.8
Classifier: Programming Language :: Python :: 3.9
Classifier: Programming Language :: Python :: 3.10
Classifier: Programming Language :: Python :: 3.11
Classifier: Programming Language :: Python :: 3.12
Classifier: Programming Language :: Python :: Implementation :: CPython
Classifier: Programming Language :: Python :: Implementation :: PyPy
Requires-Python: >=3.8
